aml-pipeline/__init__.py
aml-pipeline/adjust_coco.py
aml-pipeline/helper.py
aml-pipeline/main.py
aml-pipeline/common/__init__.py
aml-pipeline/common/analyser/__init__.py
aml-pipeline/common/analyser/benchmarking.py
aml-pipeline/common/analyser/base/__init__.py
aml-pipeline/common/analyser/base/analyser_base.py
aml-pipeline/common/analyser/error_analysis/__init__.py
aml-pipeline/common/analyser/error_analysis/classification_analysis.py
aml-pipeline/common/analyser/error_analysis/error_analyser.py
aml-pipeline/common/analyser/helper_classes/__init__.py
aml-pipeline/common/analyser/helper_classes/similarity.py
aml-pipeline/common/analyser/metrics/__init__.py
aml-pipeline/common/analyser/metrics/classification_metrics.py
aml-pipeline/common/analyser/metrics/metric_calculator.py
aml-pipeline/common/analyser/parsers/__init__.py
aml-pipeline/common/analyser/parsers/classification_parser.py
aml-pipeline/common/analyser/parsers/parser_base.py
cognitive_service_vision_model_customization_python_samples/__init__.py
cognitive_service_vision_model_customization_python_samples/clients/__init__.py
cognitive_service_vision_model_customization_python_samples/clients/client.py
cognitive_service_vision_model_customization_python_samples/clients/common.py
cognitive_service_vision_model_customization_python_samples/clients/dataset_client.py
cognitive_service_vision_model_customization_python_samples/clients/evaluation_client.py
cognitive_service_vision_model_customization_python_samples/clients/image_composition_client.py
cognitive_service_vision_model_customization_python_samples/clients/planogram_compliance_client.py
cognitive_service_vision_model_customization_python_samples/clients/prediction_client.py
cognitive_service_vision_model_customization_python_samples/clients/product_recognition_client.py
cognitive_service_vision_model_customization_python_samples/clients/training_client.py
cognitive_service_vision_model_customization_python_samples/data/__init__.py
cognitive_service_vision_model_customization_python_samples-0.0.6.dist-info/LICENSE
cognitive_service_vision_model_customization_python_samples-0.0.6.dist-info/LICENSE.md
cognitive_service_vision_model_customization_python_samples-0.0.6.dist-info/METADATA
cognitive_service_vision_model_customization_python_samples-0.0.6.dist-info/WHEEL
cognitive_service_vision_model_customization_python_samples-0.0.6.dist-info/top_level.txt
cognitive_service_vision_model_customization_python_samples-0.0.6.dist-info/RECORD
