Metadata-Version: 2.1
Name: cognitive-service-vision-model-customization-python-samples
Version: 0.0.6
Summary: A sample code repo for model customization using Python for Cognitive Service for Vision.
Home-page: 
Author: Ping Jin
License: MIT
Keywords: vision datasets classification detection
Classifier: Development Status :: 4 - Beta
Classifier: Intended Audience :: Developers
Classifier: License :: OSI Approved :: MIT License
Classifier: Programming Language :: Python :: 3.7
Classifier: Programming Language :: Python :: 3.8
Classifier: Programming Language :: Python :: 3.9
Classifier: Programming Language :: Python :: 3.10
Requires-Python: >=3.7
License-File: LICENSE
License-File: LICENSE.md
Requires-Dist: requests
Requires-Dist: tqdm
Requires-Dist: azure-storage-blob
Requires-Dist: azure-cognitiveservices-vision-customvision
Requires-Dist: cffi
Requires-Dist: opencv-python-headless
